cerebras/pytorch/__init__.py
cerebras/pytorch/_version.py
cerebras/pytorch/backends.py
cerebras/pytorch/checks.py
cerebras/pytorch/amp/__init__.py
cerebras/pytorch/amp/_amp_state.py
cerebras/pytorch/amp/_process_optimizer.py
cerebras/pytorch/amp/amp.py
cerebras/pytorch/amp/autocast.py
cerebras/pytorch/amp/compat.py
cerebras/pytorch/amp/conditional_update.py
cerebras/pytorch/amp/grad_scaler.py
cerebras/pytorch/amp/handle.py
cerebras/pytorch/amp/optimizer_step.py
cerebras/pytorch/amp/rnn_compat.py
cerebras/pytorch/amp/utils.py
cerebras/pytorch/amp/wrap.py
cerebras/pytorch/amp/lists/__init__.py
cerebras/pytorch/amp/lists/functional_overrides.py
cerebras/pytorch/amp/lists/tensor_overrides.py
cerebras/pytorch/amp/lists/torch_overrides.py
cerebras/pytorch/backend/__init__.py
cerebras/pytorch/backend/base_backend.py
cerebras/pytorch/backend/cpu_backend.py
cerebras/pytorch/backend/gpu_backend.py
cerebras/pytorch/backend/ltc_backend.py
cerebras/pytorch/core/__init__.py
cerebras/pytorch/core/annotation.py
cerebras/pytorch/core/appliance.py
cerebras/pytorch/core/appliance_utils.py
cerebras/pytorch/core/compile.py
cerebras/pytorch/core/constants.py
cerebras/pytorch/core/device.py
cerebras/pytorch/core/function_mode.py
cerebras/pytorch/core/modes.py
cerebras/pytorch/core/name_scope.py
cerebras/pytorch/core/tensor.py
cerebras/pytorch/cs_op_lib/__init__.py
cerebras/pytorch/cs_op_lib/attributes.py
cerebras/pytorch/cs_op_lib/data_containers.py
cerebras/pytorch/cs_op_lib/errors.py
cerebras/pytorch/cs_op_lib/ulp.py
cerebras/pytorch/cs_op_lib/constraints/__init__.py
cerebras/pytorch/cs_op_lib/constraints/base.py
cerebras/pytorch/cs_op_lib/constraints/composite.py
cerebras/pytorch/cs_op_lib/constraints/functional.py
cerebras/pytorch/cs_op_lib/constraints/null.py
cerebras/pytorch/cs_op_lib/constraints/operand.py
cerebras/pytorch/cs_op_lib/constraints/tensor.py
cerebras/pytorch/cs_op_lib/ops/__init__.py
cerebras/pytorch/cs_op_lib/ops/base.py
cerebras/pytorch/cs_op_lib/ops/definitions.py
cerebras_pytorch-2.9.0.dist-info/LICENSE
cerebras_pytorch-2.9.0.dist-info/METADATA
cerebras_pytorch-2.9.0.dist-info/WHEEL
cerebras_pytorch-2.9.0.dist-info/top_level.txt
cerebras_pytorch-2.9.0.dist-info/RECORD
