Metadata-Version: 2.1
Name: cerebras-pytorch
Version: 2.9.0
Summary: PyTorch support for Cerebras Wafer Scale Cluster and ML research
Home-page: https://cerebras.net/
Author: Cerebras Systems
Author-email: support@cerebras.net
Classifier: Development Status :: 5 - Production/Stable
Classifier: Intended Audience :: Developers
Classifier: Intended Audience :: Science/Research
Classifier: License :: OSI Approved :: BSD License
Classifier: Topic :: Scientific/Engineering :: Artificial Intelligence
Classifier: Topic :: Software Development
Classifier: Topic :: Software Development :: Libraries
Classifier: Topic :: System :: Hardware
Classifier: Programming Language :: Python :: 3
License-File: LICENSE
Requires-Dist: pip (>=21.1.2)
Requires-Dist: numpy (==1.25.0)
Requires-Dist: pandas (==2.2.3)
Requires-Dist: protobuf (==4.21.12)
Requires-Dist: grpcio (==1.51.1)
Requires-Dist: grpcio-tools (==1.51.1)
Requires-Dist: multiprocess (==0.70.16)
Requires-Dist: boto3
Requires-Dist: dill (==0.3.8)
Requires-Dist: tblib (==3.0.0)
Requires-Dist: tqdm (>=4.42.1)
Requires-Dist: psutil (==7.1.3)
Requires-Dist: urllib3 (<3)
Requires-Dist: tabulate (==0.9.0)
Requires-Dist: tensorboard (==2.17.1)
Requires-Dist: torch (==2.4.0)
Requires-Dist: cerebras-appliance (==2.9.0)
